{
    "discography": [
        {
            "image": "partytonightftfalafeljake.jpg",
            "title": "Party Tonight (ft. FalafelJake)",
            "author": "Japkozjad",
            "streaming": "https://push.fm/fl/823rglaj",
            "youtube": "https://youtu.be/b4N5-R8TIOg"
        },
        {
            "image": "dreamland.jpg",
            "title": "Dreamland",
            "author": "Japkozjad, Acid Applejack",
            "streaming": "https://push.fm/fl/ihairewt",
            "youtube": "https://youtube.com/watch?v=womrqZZNgA0"
        },
        {
            "image": "theemotionalvoyage.jpg",
            "title": "The Emotional Voyage",
            "author": "Japkozjad",
            "streaming": "https://push.fm/fl/9ezev8zj",
            "youtube": "https://youtu.be/JlpSQBqwmpM"
        },
        {
            "image": "ajourneyintwosteps.jpg",
            "title": "A Journey In Two Steps",
            "author": "Japkozjad",
            "streaming": "https://push.fm/fl/rc5grct5",
            "youtube": "https://youtu.be/g8xiJ3HNEYA"
        },
        {
            "image": "rainbowfactoryremix.jpg",
            "title": "Rainbow Factory (Cover/Remix)",
            "author": "WoodenToaster, Japkozjad, Hiverro",
            "streaming": null,
            "youtube": "https://youtu.be/9U9frRM3nwI"
        },
        {
            "image": "leak.jpg",
            "title": "Leak (Better Go Run)",
            "author": "Japkozjad",
            "streaming": "https://push.fm/fl/1lwbqj4b",
            "youtube": "https://youtu.be/t39iW0GURmw" 
        },
        {
            "image": "dayandeystheme.jpg",
            "title": "DayanDey's Theme",
            "author": "Japkozjad",
            "streaming": "https://push.fm/fl/wga131ef",
            "youtube": "https://youtu.be/K89JjT-JvJE"
        },
        {
            "image": "kerfu5.jpg",
            "title": "Kerfu5 [EP]",
            "author": "Japkozjad",
            "streaming": "https://push.fm/fl/axtnphqr",
            "youtube": "https://youtu.be/KISKBOD4JCU"
        },
        {
            "image": "withoutyouachoo.jpg",
            "title": "Without You (A Choo) [I'm Blue Ponified Cover]",
            "author": "Japkozjad",
            "streaming": null,
            "youtube": "https://youtu.be/_n0k4t6GJEg"
        },
        {
            "image": "drunk.jpg",
            "title": "Drunk",
            "author": "Japkozjad",
            "streaming": "https://push.fm/fl/nqusaare",
            "youtube": "https://youtu.be/LdxUS9ookas"
        },
        {
            "image": "gravity.jpg",
            "title": "Gravity",
            "author": "Japkozjad",
            "streaming": "https://push.fm/fl/nlknb9lk",
            "youtube": "https://youtu.be/SC9dbKRKbkM"
        },
        {
            "image": null,
            "title": "Tęsknię za Tobą (Japkozjad Remix)",
            "author": "Tina, ReMiXu",
            "streaming": null,
            "youtube": "https://youtu.be/iNfngcXcBHA"
        },
        {
            "image": "cirrus.jpg",
            "title": "Cirrus",
            "author": "Japkozjad",
            "streaming": "https://push.fm/fl/y5llkgqe",
            "youtube": "https://youtu.be/lcQeuRPH8M4"
        },
        {
            "image": "emergency.jpg",
            "title": "Emergency",
            "author": "Japkozjad",
            "streaming": null,
            "youtube": "https://youtu.be/UuKLm2eBbKQ"
        },
        {
            "image": "motivation.jpg",
            "title": "Motivation",
            "author": "Japkozjad",
            "streaming": "https://derpy.me/japkozjad-motivation",
            "youtube": "https://youtu.be/YUjxxJSjoj0"
        },
        {
            "image": "chill.jpg",
            "title": "Chill",
            "author": "Japkozjad",
            "streaming": "https://derpy.me/japkozjad-chill",
            "youtube": "https://youtu.be/vCDBkRrvZNM"
        },
        {
            "image": "pegasihouse.jpg",
            "title": "PegasiHouse",
            "author": "Japkozjad, Virus Ponies",
            "streaming": "https://derpy.me/pegasihouse",
            "youtube": "https://youtu.be/IhBP8h_dVg4"
        },
        {
            "image": "sunshine.jpg",
            "title": "Sunshine",
            "author": "Japkozjad",
            "streaming": null,
            "youtube": "https://youtu.be/0OsNYkUfKKY"
        },
        {
            "image": "lunardrop.jpg",
            "title": "Lunar Drop",
            "author": "Japkozjad",
            "streaming": null,
            "youtube": "https://youtu.be/2tM6dYF5mRQ"
        },
        {
            "image": "smile!.jpg",
            "title": "Smile!",
            "author": "Japkozjad, Altius Volantis",
            "streaming": "https://soundcloud.com/japkozjad/smile",
            "youtube": "https://youtu.be/PSbjhGRQABE"
        },
        {
            "image": "hipinkiepie.jpg",
            "title": "Hi! (Pinkie Pie)",
            "author": "Japkozjad",
            "streaming": null,
            "youtube": "https://youtu.be/ttBTv1DDzLc"
        },
        {
            "image": "ohmywait.jpg",
            "title": "Oh My... WAIT",
            "author": "Japkozjad",
            "streaming": null,
            "youtube": "https://youtu.be/yOEoMAVkFHQ"
        },
        {
            "image": "space.jpg",
            "title": "Space",
            "author": "Japkozjad",
            "streaming": null,
            "youtube": "https://youtu.be/ea-P18egSo0"
        },
        {
            "image": "runaway.jpg",
            "title": "Runaway",
            "author": "Japkozjad",
            "streaming": "https://open.spotify.com/track/30a4D4C7ePzmRcbF5X0gHb?si=dc6fa15fc540436c",
            "youtube": "https://youtu.be/T1roBNFiYgg"
        }
    ]
}